{"api.md":"Co8rWQyP","development_contribute.md":"CCtAJbuC","development_contributors.md":"BGb7-IPU","get_started.md":"CT4-fbWt","index.md":"CWhMMoSO","tutorials_mean_seasonal_cycle.md":"DRHgeqyI","tutorials_other_tutorials.md":"htsw4bdx","tutorials_plottingmaps.md":"CyuSILsN","userguide_cache.md":"DG586r7X","userguide_chunk.md":"JJbkwpLA","userguide_combine.md":"DWqX1mer","userguide_compute.md":"DvxBQP6e","userguide_convert.md":"BcZ_iCbO","userguide_create.md":"BqCHp-B2","userguide_faq.md":"v8QpTXKA","userguide_group.md":"BZEFN1yv","userguide_plot.md":"uZFRzgM9","userguide_read.md":"C75VsPPb","userguide_select.md":"CZfLod5X","userguide_types.md":"BnvucgU3","userguide_write.md":"Y-cFWFLX"}
